webapp1/__init__.py
webapp1/admin.py
webapp1/apps.py
webapp1/forms.py
webapp1/models.py
webapp1/tests.py
webapp1/token.py
webapp1/urls.py
webapp1/views.py
webapp1/migrations/0001_initial.py
webapp1/migrations/__init__.py
webapp1/static/css/Login1.css
webapp1/static/css/Login_form.css
webapp1/static/css/Registration_form.css
webapp1/static/css/admin.css
webapp1/static/css/all.min.css
webapp1/static/css/animate.css
webapp1/static/css/boot.css
webapp1/static/css/boot1.css
webapp1/static/css/boot_min.css
webapp1/static/css/bootstrap.min.css
webapp1/static/css/brands.2c303be1.css
webapp1/static/css/changelists.css
webapp1/static/css/dark.css
webapp1/static/css/delete.jpg
webapp1/static/css/delete.svg
webapp1/static/css/final.css
webapp1/static/css/font_awesome.min.css
webapp1/static/css/fontawesome.6002a161.css
webapp1/static/css/hamburgers.min.css
webapp1/static/css/icon-yes.svg
webapp1/static/css/image.css
webapp1/static/css/jsdelivr.css
webapp1/static/css/light.css
webapp1/static/css/login.css
webapp1/static/css/main.css
webapp1/static/css/mdb.min.css
webapp1/static/css/menu.css
webapp1/static/css/nav_sidebar.css
webapp1/static/css/navbar.css
webapp1/static/css/navbar.scss
webapp1/static/css/password_reset.css
webapp1/static/css/password_reset_form.css
webapp1/static/css/password_reset_form_base.css
webapp1/static/css/reg.css
webapp1/static/css/reg1.css
webapp1/static/css/registration.css
webapp1/static/css/regular.98fbf39a.css
webapp1/static/css/reminder.css
webapp1/static/css/responsive.css
webapp1/static/css/sample.css
webapp1/static/css/sample1.css
webapp1/static/css/sample2.css
webapp1/static/css/select2.min.css
webapp1/static/css/simple.css
webapp1/static/css/smtp1.css
webapp1/static/css/smtp2.css
webapp1/static/css/smtp3.css
webapp1/static/css/smtp4.css
webapp1/static/css/smtp5.css
webapp1/static/css/solid.c3b5f0b5.css
webapp1/static/css/style.min.css
webapp1/static/css/success.png
webapp1/static/css/test.css
webapp1/static/css/theme.css
Nagababu_Django_Webapps-0.0.2.dist-info/LICENSE.txt
Nagababu_Django_Webapps-0.0.2.dist-info/METADATA
Nagababu_Django_Webapps-0.0.2.dist-info/WHEEL
Nagababu_Django_Webapps-0.0.2.dist-info/top_level.txt
Nagababu_Django_Webapps-0.0.2.dist-info/RECORD
