Metadata-Version: 2.1
Name: Nagababu-Django-Webapps
Version: 0.0.2
Summary: A Django app to order food items through web either online or offline.
Home-page: https://github.com/Nagababu995/Django-Food-Webapps
Author: Upputuri Nagababu
Author-email: nagababuuupputuri@gmail.com
License: MIT  # Example license
Platform: UNKNOWN
Classifier: Environment :: Web Environment
Classifier: Framework :: Django
Classifier: Framework :: Django
Classifier: Intended Audience :: Developers
Classifier: License :: OSI Approved :: MIT License
Classifier: Operating System :: OS Independent
Classifier: Programming Language :: Python :: 3.9
Classifier: Programming Language :: Python :: 3.6
Classifier: Programming Language :: Python :: 3.7
Classifier: Programming Language :: Python :: 3.8
Classifier: Topic :: Internet :: WWW/HTTP
Classifier: Topic :: Internet :: WWW/HTTP :: Dynamic Content
Requires-Python: >=3.6
License-File: LICENSE.txt
Requires-Dist: Django
Requires-Dist: crispy
Requires-Dist: django-crispy-forms
Requires-Dist: django-widget-tweaks
Requires-Dist: Pillow
Requires-Dist: pytest
Requires-Dist: razorpay
Requires-Dist: six
Requires-Dist: selenium
Requires-Dist: html-testRunner
